{
  "mcpServers": {
    "perception": {
      "command": "node",
      "args": [],
      "url": "http://127.0.0.1:42069",
      "transport": "http",
      "description": "Perception.cx MCP server — JSON-RPC over local HTTP. Launched automatically by the Perception IDE when MCP is enabled in settings (Settings → Perception MCP). Loopback-only. Tool names below are the live JSON-RPC method names, kept in sync with docs/perception/mcp-api.md by tools/check-mcp-config.py (CI).",
      "tools": [
        "process/list",
        "process/info_by_pid",
        "process/info_by_name",
        "process/reference_by_pid",
        "process/reference_by_name",
        "process/dereference",
        "process/cleanup_references",
        "process/list_references",
        "process/read_virtual_memory",
        "process/write_virtual_memory",
        "process/is_valid_address",
        "process/read_typed_value",
        "process/write_typed_value",
        "process/read_string",
        "process/write_string",
        "process/copy_memory",
        "process/fill_memory",
        "process/read_pointer_chain",
        "process/disassemble",
        "process/get_modules",
        "process/get_threads",
        "process/get_module_by_name",
        "process/get_export_address",
        "process/get_import_address",
        "process/get_module_imports",
        "process/list_module_exports",
        "process/get_module_sections",
        "process/get_pe_header",
        "process/get_module_strings",
        "process/get_exception_table",
        "process/get_data_directory",
        "process/query_memory_region",
        "process/enumerate_memory_regions",
        "process/allocate_memory",
        "process/free_memory",
        "process/find_pattern",
        "process/find_all_patterns",
        "process/scan_value",
        "process/scan_next",
        "process/scan_string",
        "process/scan_pointer_to",
        "process/find_xrefs",
        "process/find_string_refs",
        "process/generate_signature",
        "process/diff_memory",
        "process/find_function_bounds",
        "process/find_function_by_signature",
        "process/analyze_vtable",
        "process/read_rtti",
        "process/lookup_symbol",
        "process/find_function_by_name",
        "process/enum_handles",
        "system/info",
        "system/list_drivers",
        "process/get_command_line",
        "process/list_environment",
        "script/get_context",
        "script/validate",
        "script/execute"
      ]
    }
  }
}